abi3audit/__init__.py
abi3audit/__main__.py
abi3audit/_audit.py
abi3audit/_cache.py
abi3audit/_cli.py
abi3audit/_extract.py
abi3audit/_object.py
abi3audit/_state.py
abi3audit/_vendor/__init__.py
abi3audit/_vendor/asn1_der.py
abi3audit/_vendor/mach_o.py
abi3audit-0.0.23.dist-info/entry_points.txt
abi3audit-0.0.23.dist-info/licenses/LICENSE
abi3audit-0.0.23.dist-info/WHEEL
abi3audit-0.0.23.dist-info/METADATA
abi3audit-0.0.23.dist-info/RECORD
