Metadata-Version: 2.4
Name: abi3audit
Version: 0.0.23
Summary: Scans Python wheels for abi3 violations and inconsistencies
Author-email: William Woodruff <william@trailofbits.com>
Requires-Python: >=3.10
License-Expression: MIT
Classifier: Programming Language :: Python :: 3 :: Only
Classifier: Programming Language :: Python :: 3
Classifier: Development Status :: 4 - Beta
Classifier: Intended Audience :: Developers
Classifier: Topic :: Security
License-File: LICENSE
Requires-Dist: abi3info >= 2024.06.19
Requires-Dist: kaitaistruct ~= 0.10
Requires-Dist: packaging >= 21.3,< 26.0
Requires-Dist: pefile >= 2022.5.30
Requires-Dist: pyelftools >= 0.29
Requires-Dist: requests >= 2.28.1,< 2.33.0
Requires-Dist: requests-cache >= 0.9.6,< 1.3.0
Requires-Dist: rich >= 12.5.1,< 14.3.0
Project-URL: Homepage, https://pypi.org/project/abi3audit/
Project-URL: Issues, https://github.com/pypa/abi3audit/issues
Project-URL: Source, https://github.com/pypa/abi3audit
